Workbook

Sheet EDT
A1: Etapas | B1: DIAS | C1: HORAS POR ACTIVIDAD O ENTREGABLE / DÍA
A2: Sprint 1 | Planificación, Análisis y Diseño | C2: Jefe de Proyecto | D2: Analista Programador | E2: DBA | F2: QA | G2: Diseñador | I2: DICCIONARIO EDT
A3: Organización del equipo | B3: 8 | C3: 8 | D3: 8 | E3: 0 | F3: 0 | G3: 0 | I3: ROL ACTOR | J3: NOMBRE ACTOR
A4: Definicion Proyecto APT | B4: 4 | C4: 6 | D4: 6 | E4: 1 | F4: 1 | G4: 2 | I4: Jefe de Proyecto | J4: Diego Quiroz
A5: Documentos Individuales | B5: 2 | C5: 8 | D5: 8 | E5: 0 | F5: 0 | G5: 0 | I5: Analista Programador | J5: Noelia Peña
A6: Acta de Constitución de proyecto | B6: 1 | C6: 6 | D6: 6 | E6: 1 | F6: 1 | G6: 2 | I6: DBA | J6: Diego Quiroz
A7: Aprobación del Acta | B7: 1 | C7: 8 | D7: 8 | E7: 0 | F7: 0 | G7: 0 | I7: QA | J7: Diego Quiroz
A8: Definición de requerimientos Generales | B8: 2 | C8: 4 | D8: 6 | E8: 2 | F8: 2 | G8: 2 | I8: Diseñador | J8: Noelia Peña
A9: Captura de requerimientos específicos | B9: 2 | C9: 4 | D9: 6 | E9: 2 | F9: 2 | G9: 2
A10: Documento de casos de uso extendido | B10: 1 | C10: 3 | D10: 4 | E10: 3 | F10: 2 | G10: 4
A11: Prototipos | B11: 3 | C11: 4 | D11: 3 | E11: 2 | F11: 2 | G11: 5
A12: Propuesta ERS | B12: 3 | C12: 5 | D12: 5 | E12: 2 | F12: 1 | G12: 3
A13: Matriz EDT | B13: 1 | C13: 8 | D13: 8 | E13: 0 | F13: 0 | G13: 0
A14: Documentos de Presentación de Proyecto | B14: 1 | C14: 8 | D14: 8 | E14: 0 | F14: 0 | G14: 0
A15: Sprint 2 | Desarrollo de la aplicación móvil | C15: Jefe de Proyecto | D15: Analista Programador | E15: DBA | F15: QA | G15: Diseñador
A16: Documento DAS | B16: 2 | C16: 3 | D16: 4 | E16: 3 | F16: 2 | G16: 4
A17: Documento Proceso de Negocios | B17: 2 | C17: 6 | D17: 6 | E17: 1 | F17: 1 | G17: 2
A18: Matriz RACI | B18: 2 | C18: 6 | D18: 6 | E18: 1 | F18: 1 | G18: 2
A19: Matriz de Riesgo | B19: 2 | C19: 6 | D19: 6 | E19: 1 | F19: 1 | G19: 2
A20: Flujo de caja | B20: 2 | C20: 8 | D20: 8 | E20: 0 | F20: 0 | G20: 0
A21: Diccionario de Datos | B21: 2 | C21: 4 | D21: 8 | E21: 4 | F21: 0 | G21: 0
A22: Desarrollo de la Base de Datos | B22: 5 | C22: 2 | D22: 8 | E22: 6 | F22: 0 | G22: 0
A23: Desarrollo Módulo de Autenticación y Perfil | B23: 5 | C23: 2 | D23: 8 | E23: 6 | F23: 0 | G23: 0
A24: Desarrollo Módulo de Productos y Búsqueda | B24: 5 | C24: 2 | D24: 8 | E24: 6 | F24: 0 | G24: 0
A25: Desarrollo Módulo Principal de Colección | B25: 5 | C25: 2 | D25: 8 | E25: 6 | F25: 0 | G25: 0
A26: Sprint 3 | Entrenamiento e integración de modelo IA a APP Móvil | C26: Jefe de Proyecto | D26: Analista Programador | E26: DBA | F26: QA | G26: Diseñador
A27: Generación de repositorio de imágenes para entrenamiento | B27: 2 | C27: 2 | D27: 8 | E27: 6 | F27: 0 | G27: 0
A28: Entrenamiento de modelo IA | B28: 5 | C28: 8 | D28: 8 | E28: 0 | F28: 0 | G28: 0
A29: Integración de modelo IA con Aplicación | B29: 4 | C29: 1 | D29: 8 | E29: 5 | F29: 2 | G29: 0
A30: Sprint 4 | Certificación QA y puesta en marcha de la app | C30: Jefe de Proyecto | D30: Analista Programador | E30: DBA | F30: QA | G30: Diseñador
A31: Implementación del ambiente de pruebas | B31: 7 | C31: 2 | D31: 8 | E31: 3 | F31: 3 | G31: 0
A32: Pruebas funcionales y de usabilidad con usuarios finales | B32: 7 | C32: 2 | D32: 8 | E32: 1 | F32: 5 | G32: 0
A33: Corrección de errores y ajustes finales | B33: 7 | C33: 2 | D33: 8 | E33: 2 | F33: 4 | G33: 0
A34: Migración de la app a producción (Google Play / App Store) | B34: 7 | C34: 2 | D34: 8 | E34: 3 | F34: 3 | G34: 0
A35: Sprint 5| Presentación Final del Proyecto | C35: Jefe de Proyecto | D35: Analista Programador | E35: DBA | F35: QA | G35: Diseñador
A36: Preparación de documentación final y manuales de usuario | B36: 1 | C36: 8 | D36: 8 | E36: 0 | F36: 0 | G36: 0
A37: Acta de cierre del proyecto | B37: 1 | C37: 8 | D37: 8 | E37: 0 | F37: 0 | G37: 0
B38: =SUM(B3:B37) -> 102

Sheet Costos Fases
A2: SIGLA | B2: ROL | C2: NOMBRE | D2: VALOR HORA HH | E2: HORAS | F2: SPRINT 1 | H2: COSTO POR HORA
A3: JP | B3: Jefe de Proyecto | C3: Diego Quiroz | D3: =$J$4 -> 10000 | E3: =(EDT!B$3*EDT!C$3)+(EDT!B$4*EDT!C$4)+(EDT!B$5*EDT!C$5)+(EDT!B$6*EDT!C$6)+(EDT!B$7*EDT!C$7)+(EDT!B$8*EDT!C$8)+(EDT!B$9*EDT!C$9)+(EDT!B$10*EDT!C$10)+(EDT!B$11*EDT!C$11)+(EDT!B$12*EDT!C$12)+(EDT!B$13*EDT!C$13)+(EDT!B$14*EDT!C$14) -> 180 | F3: =D3*E3 -> 1800000 | H3: ROL | I3: NOMBRE | J3: COSTO x HORA | K3: Sueldo mes
A4: AP | B4: Analista Programador | C4: Noelia Peña | D4: =$J$5 -> 5555.5556 | E4: =(EDT!B$3*EDT!D$3)+(EDT!B$4*EDT!D$4)+(EDT!B$5*EDT!D$5)+(EDT!B$6*EDT!D$6)+(EDT!B$7*EDT!D$7)+(EDT!B$8*EDT!D$8)+(EDT!B$9*EDT!D$9)+(EDT!B$10*EDT!D$10)+(EDT!B$11*EDT!D$11)+(EDT!B$12*EDT!D$12)+(EDT!B$13*EDT!D$13)+(EDT!B$14*EDT!D$14) -> 186 | F4: =D4*E4 -> 1033333.3 | H4: Jefe de Proyecto | I4: Diego Quiroz | J4: =K4/180 -> 10000 | K4: 1800000
A5: DBA | B5: Desarrollador BD | C5: Diego Quiroz | D5: =$J$6 -> 7222.2222 | E5: =(EDT!B$3*EDT!E$3)+(EDT!B$4*EDT!E$4)+(EDT!B$5*EDT!E$5)+(EDT!B$6*EDT!E$6)+(EDT!B$7*EDT!E$7)+(EDT!B$8*EDT!E$8)+(EDT!B$9*EDT!E$9)+(EDT!B$10*EDT!E$10)+(EDT!B$11*EDT!E$11)+(EDT!B$12*EDT!E$12)+(EDT!B$13*EDT!E$13)+(EDT!B$14*EDT!E$14) -> 28 | F5: =D5*E5 -> 202222.22 | H5: Analista Programador | I5: Noelia Peña | J5: =K5/180 -> 5555.5556 | K5: 1000000
A6: QA | B6: Calidad Y Testing | C6: Diego Quiroz | D6: =$J$7 -> 7777.7778 | E6: =(EDT!B$3*EDT!F$3)+(EDT!B$4*EDT!F$4)+(EDT!B$5*EDT!F$5)+(EDT!B$6*EDT!F$6)+(EDT!B$7*EDT!F$7)+(EDT!B$8*EDT!F$8)+(EDT!B$9*EDT!F$9)+(EDT!B$10*EDT!F$10)+(EDT!B$11*EDT!F$11)+(EDT!B$12*EDT!F$12)+(EDT!B$13*EDT!F$13)+(EDT!B$14*EDT!F$14) -> 24 | F6: =D6*E6 -> 186666.67 | H6: Administrador BD | I6: Diego Quiroz | J6: =K6/180 -> 7222.2222 | K6: 1300000
A7: DI | B7: Diseñador | C7: Noelia Peña | D7: =$J$8 -> 6666.6667 | E7: =(EDT!B$3*EDT!G$3)+(EDT!B$4*EDT!G$4)+(EDT!B$5*EDT!G$5)+(EDT!B$6*EDT!C$6)+(EDT!B$7*EDT!G$7)+(EDT!B$8*EDT!G$8)+(EDT!B$9*EDT!G$9)+(EDT!B$10*EDT!G$10)+(EDT!B$11*EDT!G$11)+(EDT!B$12*EDT!G$12)+(EDT!B$13*EDT!G$13)+(EDT!B$14*EDT!G$14) -> 50 | F7: =D7*E7 -> 333333.33 | H7: Calidad Y Testing | I7: Diego Quiroz | J7: =K7/180 -> 7777.7778 | K7: 1400000
B8: TOTAL SPRINT 1 | F8: =SUM(F3:F7) -> 3555555.6 | H8: Diseñador | I8: Noelia Peña | J8: =K8/180 -> 6666.6667 | K8: 1200000
A11: SIGLA | B11: ROL | C11: NOMBRE | D11: VALOR HORA HH | E11: HORAS | F11: SPRINT 2 | H11: COSTO HH POR ROL
A12: JP | B12: Jefe de Proyecto | C12: Diego Quiroz | D12: =$J$4 -> 10000 | E12: =(EDT!B$16*EDT!C$16)+(EDT!B$17*EDT!C$17)+(EDT!B$18*EDT!C$18)+(EDT!B$19*EDT!C$19)+(EDT!B$20*EDT!C$20)+(EDT!B$21*EDT!C$21)+(EDT!B$22*EDT!C$22)+(EDT!B$23*EDT!C$23)+(EDT!B$24*EDT!C$24)+(EDT!B$25*EDT!C$25) -> 106 | F12: =D12*E12 -> 1060000 | H12: Jefe de Proyecto | I12: =F3+F12+F21+F30+F39 -> 4060000
A13: AP | B13: Analista Programador | C13: Noelia Peña | D13: =$J$5 -> 5555.5556 | E13: =(EDT!B$16*EDT!D$16)+(EDT!B$17*EDT!D$17)+(EDT!B$18*EDT!D$18)+(EDT!B$19*EDT!D$19)+(EDT!B$20*EDT!D$20)+(EDT!B$21*EDT!D$21)+(EDT!B$22*EDT!D$22)+(EDT!B$23*EDT!D$23)+(EDT!B$24*EDT!D$24)+(EDT!B$25*EDT!D$25) -> 236 | F13: =D13*E13 -> 1311111.1 | H13: Analista Programador | I13: =F4+F13+F22+F31+F40 -> 4166666.7
A14: DBA | B14: Desarrollador BD | C14: Diego Quiroz | D14: =$J$6 -> 7222.2222 | E14: =(EDT!B$16*EDT!E$16)+(EDT!B$17*EDT!E$17)+(EDT!B$18*EDT!E$18)+(EDT!B$19*EDT!E$19)+(EDT!B$20*EDT!E$20)+(EDT!B$21*EDT!E$21)+(EDT!B$22*EDT!E$22)+(EDT!B$23*EDT!E$23)+(EDT!B$24*EDT!E$24)+(EDT!B$25*EDT!E$25) -> 140 | F14: =D14*E14 -> 1011111.1 | H14: Administrador BD | I14: =F5+F14+F23+F32+F41 -> 1899444.4
A15: QA | B15: Calidad Y Testing | C15: Diego Quiroz | D15: =$J$7 -> 7777.7778 | E15: =(EDT!B$16*EDT!F$16)+(EDT!B$17*EDT!F$17)+(EDT!B$18*EDT!F$18)+(EDT!B$19*EDT!F$19)+(EDT!B$20*EDT!F$20)+(EDT!B$21*EDT!F$21)+(EDT!B$22*EDT!F$22)+(EDT!B$23*EDT!F$23)+(EDT!B$24*EDT!F$24)+(EDT!B$25*EDT!F$25) -> 10 | F15: =D15*E15 -> 77777.778 | H15: Calidad Y Testing | I15: =F6+F15+F24+F33+F42 -> 1143333.3
A16: DI | B16: Diseñador | C16: Noelia Peña | D16: =$J$8 -> 6666.6667 | E16: =(EDT!B$16*EDT!G$16)+(EDT!B$17*EDT!G$17)+(EDT!B$18*EDT!G$18)+(EDT!B$19*EDT!G$19)+(EDT!B$20*EDT!G$20)+(EDT!B$21*EDT!G$21)+(EDT!B$22*EDT!G$22)+(EDT!B$23*EDT!G$23)+(EDT!B$24*EDT!G$24)+(EDT!B$25*EDT!G$25) -> 20 | F16: =D16*E16 -> 133333.33 | H16: Diseñador | I16: =F7+F16+F25+F34+F43 -> 466666.67
B17: TOTAL SPRINT 2 | F17: =SUM(F12:F16) -> 3593333.3 | H17: TOTAL HH | I17: =SUM(I12:I16) -> 11736111
A20: SIGLA | B20: ROL | C20: NOMBRE | D20: VALOR HORA HH | E20: HORAS | F20: SPRINT 3 | H20: COSTO POR FASE
A21: JP | B21: Jefe de Proyecto | C21: Diego Quiroz | D21: =$J$4 -> 10000 | E21: =(EDT!B$27*EDT!C$27)+(EDT!B$28*EDT!C$28)+(EDT!B$29*EDT!C$29) -> 48 | F21: =D21*E21 -> 480000 | H21: Sprint 1 | Planificación, Análisis y Diseño | I21: =F8 -> 3555555.6
A22: AP | B22: Analista Programador | C22: Noelia Peña | D22: =$J$5 -> 5555.5556 | E22: =(EDT!B$27*EDT!D$27)+(EDT!B$28*EDT!D$28)+(EDT!B$29*EDT!D$29) -> 88 | F22: =D22*E22 -> 488888.89 | H22: Sprint 2 | Desarrollo de la aplicación móvil | I22: =F17 -> 3593333.3
A23: DBA | B23: Desarrollador BD | C23: Diego Quiroz | D23: =$J$6 -> 7222.2222 | E23: =(EDT!B$27*EDT!E$27)+(EDT!B$28*EDT!E$28)+(EDT!B$29*EDT!E$29) -> 32 | F23: =D23*E23 -> 231111.11 | H23: Sprint 3 | Integración y pruebas del sistema | I23: =F26 -> 1262222.2
A24: QA | B24: Calidad Y Testing | C24: Diego Quiroz | D24: =$J$7 -> 7777.7778 | E24: =(EDT!B$27*EDT!F$27)+(EDT!B$28*EDT!F$28)+(EDT!B$29*EDT!F$29) -> 8 | F24: =D24*E24 -> 62222.222 | H24: Sprint 4 | Certificación QA y puesta en marcha de la app | I24: =F35 -> 3076111.1
A25: DI | B25: Diseñador | C25: Noelia Peña | D25: =$J$8 -> 6666.6667 | E25: =(EDT!B$27*EDT!G$27)+(EDT!B$28*EDT!G$28)+(EDT!B$29*EDT!G$29) -> 0 | F25: =D25*E25 -> 0 | H25: Sprint 5| Presentación Final del Proyecto | I25: =F44 -> 248888.89
B26: TOTAL SPRINT 3 | F26: =SUM(F21:F25) -> 1262222.2 | H26: TOTAL HH FASES | I26: =SUM(I21:I25) -> 11736111
A29: SIGLA | B29: ROL | C29: NOMBRE | D29: VALOR HORA HH | E29: HORAS | F29: SPRINT 4 | H29: Margen | I29: 0.6 | J29: Es el porcentaje de beneficio deseado sobre el costo incurrido.
A30: JP | B30: Jefe de Proyecto | C30: Diego Quiroz | D30: =$J$4 -> 10000 | E30: =(EDT!B$31*EDT!C$31)+(EDT!B$32*EDT!C$32)+(EDT!B$33*EDT!C$33)+(EDT!B$34*EDT!C$34) -> 56 | F30: =D30*E30 -> 560000 | H30: UTILIDAD | I30: =I26*I29 -> 7041666.7 | J30: ganancia monetaria obtenida al aplicar el margen del 60% al costo.
A31: AP | B31: Analista Programador | C31: Noelia Peña | D31: =$J$5 -> 5555.5556 | E31: =(EDT!B$31*EDT!D$31)+(EDT!B$32*EDT!D$32)+(EDT!B$33*EDT!D$33)+(EDT!B$34*EDT!D$34) -> 224 | F31: =D31*E31 -> 1244444.4 | H31: PRECIO FINAL | I31: =I26+I30 -> 18777778 | J31: costo total mas utilidad(precio venta al cliente)
A32: DBA | B32: Desarrollador BD | C32: Diego Quiroz | D32: =$J$6 -> 7222.2222 | E32: =(EDT!B$31*EDT!E$31)+(EDT!B$32*EDT!E$32)+(EDT!B$33*EDT!E$33)+(EDT!B$34*EDT!E$34) -> 63 | F32: =D32*E32 -> 455000
A33: QA | B33: Calidad Y Testing | C33: Diego Quiroz | D33: =$J$7 -> 7777.7778 | E33: =(EDT!B$31*EDT!F$31)+(EDT!B$32*EDT!F$32)+(EDT!B$33*EDT!F$33)+(EDT!B$34*EDT!F$34) -> 105 | F33: =D33*E33 -> 816666.67
A34: DI | B34: Diseñador | C34: Noelia Peña | D34: =$J$8 -> 6666.6667 | E34: =(EDT!B$31*EDT!G$31)+(EDT!B$32*EDT!G$32)+(EDT!B$33*EDT!G$33)+(EDT!B$34*EDT!G$34) -> 0 | F34: =D34*E34 -> 0
B35: TOTAL SPRINT 4 | F35: =SUM(F30:F34) -> 3076111.1
A38: SIGLA | B38: ROL | C38: NOMBRE | D38: VALOR HORA HH | E38: HORAS | F38: SPRINT 5
A39: JP | B39: Jefe de Proyecto | C39: Diego Quiroz | D39: =$J$4 -> 10000 | E39: =(EDT!B$36*EDT!C$36)+(EDT!B$37*EDT!C$37) -> 16 | F39: =D39*E39 -> 160000
A40: AP | B40: Analista Programador | C40: Noelia Peña | D40: =$J$5 -> 5555.5556 | E40: =(EDT!B$36*EDT!D$36)+(EDT!B$37*EDT!D$37) -> 16 | F40: =D40*E40 -> 88888.889
A41: DBA | B41: Desarrollador BD | C41: Diego Quiroz | D41: =$J$6 -> 7222.2222 | E41: =(EDT!B$36*EDT!E$36)+(EDT!B$37*EDT!E$37) -> 0 | F41: =D41*E41 -> 0
A42: QA | B42: Calidad Y Testing | C42: Diego Quiroz | D42: =$J$7 -> 7777.7778 | E42: =(EDT!B$36*EDT!F$36)+(EDT!B$37*EDT!F$37) -> 0 | F42: =D42*E42 -> 0
A43: DI | B43: Diseñador | C43: Noelia Peña | D43: =$J$8 -> 6666.6667 | E43: =(EDT!B$36*EDT!G$36)+(EDT!B$37*EDT!G$37) -> 0 | F43: =D43*E43 -> 0
B44: TOTAL SPRINT 5 | F44: =SUM(F39:F43) -> 248888.89
